LICENSE
MANIFEST.in
README
TODO
setup.py
django_easymode.egg-info/PKG-INFO
django_easymode.egg-info/SOURCES.txt
django_easymode.egg-info/dependency_links.txt
django_easymode.egg-info/namespace_packages.txt
django_easymode.egg-info/not-zip-safe
django_easymode.egg-info/requires.txt
django_easymode.egg-info/top_level.txt
docs/Makefile
docs/api.rst
docs/changes.rst
docs/commands.rst
docs/conf.py
docs/debug.rst
docs/details.rst
docs/fields.rst
docs/index.rst
docs/middleware.rst
docs/settings.rst
docs/templatetags.rst
docs/i18n/api.rst
docs/i18n/index.rst
docs/i18n/localized.png
docs/i18n/non-localized.png
docs/i18n/translation.rst
docs/tree/api.rst
docs/tree/index.rst
docs/tree/invisible.png
docs/tree/newtree.png
docs/tree/oldtree.rst
docs/tree/related.png
docs/utils/api.rst
docs/xslt/api.rst
docs/xslt/helpers.rst
docs/xslt/index.rst
easymode/__init__.py
easymode/middleware.py
easymode/models.py
easymode/pip-log.txt
easymode/urls.py
easymode/views.py
easymode/.ropeproject/config.py
easymode/admin/__init__.py
easymode/admin/abstract.py
easymode/admin/fields.py
easymode/admin/utils.py
easymode/admin/forms/__init__.py
easymode/admin/forms/fields.py
easymode/admin/models/__init__.py
easymode/admin/models/fields.py
easymode/debug/__init__.py
easymode/debug/middleware.py
easymode/i18n/__init__.py
easymode/i18n/decorators.py
easymode/i18n/gettext.py
easymode/i18n/admin/__init__.py
easymode/i18n/admin/decorators.py
easymode/i18n/admin/forms.py
easymode/i18n/admin/generic.py
easymode/i18n/admin/widgets.py
easymode/i18n/meta/__init__.py
easymode/i18n/meta/fields.py
easymode/i18n/meta/utils.py
easymode/i18n/meta/value.py
easymode/locale/en/LC_MESSAGES/django.po
easymode/locale/it/LC_MESSAGES/django.po
easymode/locale/nl/LC_MESSAGES/django.po
easymode/management/__init__.py
easymode/management/commands/__init__.py
easymode/management/commands/easy_copy_language.py
easymode/management/commands/easy_locale.py
easymode/management/commands/easy_reset_language.py
easymode/media/easymode/js/adminoverride.js
easymode/media/easymode/js/menu-sort.js
easymode/templates/admin/index.html
easymode/templates/i18n/po_header.txt
easymode/templates/tree/admin/change_form_with_parent_link.html
easymode/templates/tree/admin/change_form_with_related_links.html
