Metadata-Version: 1.1
Name: django-easymode
Version: 1.4b5
Summary: Quickly build backends for flash/flex websites with django
Home-page: http://github.com/specialunderwear/django-easymode
Author: L. van de Kerkhof
Author-email: easymode@librelist.com
License: GPL
Keywords: adobe flex flash xml xslt i18n internationalization translate django
Platform: any
Classifier: Development Status :: 4 - Beta
Classifier: Environment :: Console
Classifier: Environment :: Web Environment
Classifier: Framework :: Django
Classifier: Intended Audience :: Developers
Classifier: License :: OSI Approved :: GNU General Public License (GPL)
Classifier: Operating System :: MacOS :: MacOS X
Classifier: Operating System :: POSIX
Classifier: Programming Language :: Python
Classifier: Programming Language :: Python :: 2.6
Classifier: Topic :: Internet :: WWW/HTTP :: Dynamic Content
Classifier: Topic :: Internet :: WWW/HTTP :: Site Management
Classifier: Topic :: Software Development :: Localization
